dingtalk_simple_test/__init__.py
dingtalk_simple_test/api/__init__.py
dingtalk_simple_test/api/base.py
dingtalk_simple_test/api/callback.py
dingtalk_simple_test/api/department.py
dingtalk_simple_test/api/user.py
dingtalk_simple_test/client/__init__.py
dingtalk_simple_test/client/base.py
dingtalk_simple_test/core/__init__.py
dingtalk_simple_test/core/constants.py
dingtalk_simple_test/core/exceptions.py
dingtalk_simple_test/core/utils.py
dingtalk_simple_test/crypto/__init__.py
dingtalk_simple_test/crypto/base.py
dingtalk_simple_test/crypto/cryptography.py
dingtalk_simple_test/crypto/pkcs7.py
dingtalk_simple_test/crypto/pycrypto.py
dingtalk_simple_test/storage/__init__.py
dingtalk_simple_test/storage/base.py
dingtalk_simple_test-0.0.2.dist-info/LICENSE
dingtalk_simple_test-0.0.2.dist-info/METADATA
dingtalk_simple_test-0.0.2.dist-info/WHEEL
dingtalk_simple_test-0.0.2.dist-info/top_level.txt
dingtalk_simple_test-0.0.2.dist-info/RECORD
