Metadata-Version: 2.1
Name: dingtalk-simple-test
Version: 0.0.2
Summary: python dingtalk simple sdk
Home-page: https://github.com/pypa/sampleproject
Author: Panda
Author-email: josh_zhou@hotmail.com
License: UNKNOWN
Platform: UNKNOWN
Classifier: Programming Language :: Python :: 2.7
Classifier: License :: OSI Approved :: MIT License
Classifier: Operating System :: OS Independent
